{
	"$schema": "http://schema.management.azure.com/schemas/2015-01-01/deploymentTemplate.json#",
	"contentVersion": "1.0.0.0",
	"parameters": {
		"factoryName": {
			"type": "string",
			"metadata": "Data Factory name",
			"defaultValue": "sagardatafactorycloud"
		},
		"AbhishekDB_LS_connectionString": {
			"type": "secureString",
			"metadata": "Secure string for 'connectionString' of 'AbhishekDB_LS'"
		},
		"ClientDBLinkedServer_connectionString": {
			"type": "secureString",
			"metadata": "Secure string for 'connectionString' of 'ClientDBLinkedServer'"
		},
		"DatabricksSagar_LS_accessToken": {
			"type": "secureString",
			"metadata": "Secure string for 'accessToken' of 'DatabricksSagar_LS'"
		},
		"Gen2Storage_LS_accountKey": {
			"type": "secureString",
			"metadata": "Secure string for 'accountKey' of 'Gen2Storage_LS'"
		},
		"sqlserversagarSagarDB_LS_connectionString": {
			"type": "secureString",
			"metadata": "Secure string for 'connectionString' of 'sqlserversagarSagarDB_LS'"
		},
		"DatabricksSagar_LS_properties_typeProperties_existingClusterId": {
			"type": "string",
			"defaultValue": "0624-151633-ghpftm79"
		},
		"Gen2Storage_LS_properties_typeProperties_url": {
			"type": "string",
			"defaultValue": "https://storageaccountgen2sagar.dfs.core.windows.net/"
		}
	},
	"variables": {
		"factoryId": "[concat('Microsoft.DataFactory/factories/', parameters('factoryName'))]"
	},
	"resources": [
		{
			"name": "[concat(parameters('factoryName'), '/My2ndPipelineforGit')]",
			"type": "Microsoft.DataFactory/factories/pipelines",
			"apiVersion": "2018-06-01",
			"properties": {
				"activities": [
					{
						"name": "Wait1",
						"type": "Wait",
						"dependsOn": [],
						"userProperties": [],
						"typeProperties": {
							"waitTimeInSeconds": 1
						}
					}
				],
				"policy": {
					"elapsedTimeMetric": {},
					"cancelAfter": {}
				},
				"annotations": []
			},
			"dependsOn": []
		},
		{
			"name": "[concat(parameters('factoryName'), '/futurebranch_pipeline')]",
			"type": "Microsoft.DataFactory/factories/pipelines",
			"apiVersion": "2018-06-01",
			"properties": {
				"activities": [
					{
						"name": "Wait1",
						"type": "Wait",
						"dependsOn": [],
						"userProperties": [],
						"typeProperties": {
							"waitTimeInSeconds": 1
						}
					}
				],
				"policy": {
					"elapsedTimeMetric": {},
					"cancelAfter": {}
				},
				"annotations": []
			},
			"dependsOn": []
		},
		{
			"name": "[concat(parameters('factoryName'), '/AbhishekDB_LS')]",
			"type": "Microsoft.DataFactory/factories/linkedServices",
			"apiVersion": "2018-06-01",
			"properties": {
				"annotations": [],
				"type": "AzureSqlDatabase",
				"typeProperties": {
					"connectionString": "[parameters('AbhishekDB_LS_connectionString')]"
				}
			},
			"dependsOn": []
		},
		{
			"name": "[concat(parameters('factoryName'), '/ClientDBLinkedServer')]",
			"type": "Microsoft.DataFactory/factories/linkedServices",
			"apiVersion": "2018-06-01",
			"properties": {
				"annotations": [],
				"type": "AzureSqlDatabase",
				"typeProperties": {
					"connectionString": "[parameters('ClientDBLinkedServer_connectionString')]"
				}
			},
			"dependsOn": []
		},
		{
			"name": "[concat(parameters('factoryName'), '/DatabricksSagar_LS')]",
			"type": "Microsoft.DataFactory/factories/linkedServices",
			"apiVersion": "2018-06-01",
			"properties": {
				"annotations": [],
				"type": "AzureDatabricks",
				"typeProperties": {
					"domain": "https://adb-4526287489866767.7.azuredatabricks.net",
					"accessToken": {
						"type": "SecureString",
						"value": "[parameters('DatabricksSagar_LS_accessToken')]"
					},
					"existingClusterId": "[parameters('DatabricksSagar_LS_properties_typeProperties_existingClusterId')]"
				}
			},
			"dependsOn": []
		},
		{
			"name": "[concat(parameters('factoryName'), '/Gen2Storage_LS')]",
			"type": "Microsoft.DataFactory/factories/linkedServices",
			"apiVersion": "2018-06-01",
			"properties": {
				"annotations": [],
				"type": "AzureBlobFS",
				"typeProperties": {
					"url": "[parameters('Gen2Storage_LS_properties_typeProperties_url')]",
					"accountKey": {
						"type": "SecureString",
						"value": "[parameters('Gen2Storage_LS_accountKey')]"
					}
				}
			},
			"dependsOn": []
		},
		{
			"name": "[concat(parameters('factoryName'), '/sqlserversagarSagarDB_LS')]",
			"type": "Microsoft.DataFactory/factories/linkedServices",
			"apiVersion": "2018-06-01",
			"properties": {
				"annotations": [],
				"type": "AzureSqlDatabase",
				"typeProperties": {
					"connectionString": "[parameters('sqlserversagarSagarDB_LS_connectionString')]"
				}
			},
			"dependsOn": []
		},
		{
			"name": "[concat(parameters('factoryName'), '/RunNotebook_PL')]",
			"type": "Microsoft.DataFactory/factories/pipelines",
			"apiVersion": "2018-06-01",
			"properties": {
				"activities": [
					{
						"name": "Notebook1",
						"type": "DatabricksNotebook",
						"dependsOn": [],
						"policy": {
							"timeout": "0.12:00:00",
							"retry": 0,
							"retryIntervalInSeconds": 30,
							"secureOutput": false,
							"secureInput": false
						},
						"userProperties": [],
						"typeProperties": {
							"notebookPath": "/cloudconnectionedu@outlook.com/MyDatabrickFirstNotebook"
						},
						"linkedServiceName": {
							"referenceName": "DatabricksSagar_LS",
							"type": "LinkedServiceReference"
						}
					}
				],
				"policy": {
					"elapsedTimeMetric": {},
					"cancelAfter": {}
				},
				"annotations": []
			},
			"dependsOn": [
				"[concat(variables('factoryId'), '/linkedServices/DatabricksSagar_LS')]"
			]
		},
		{
			"name": "[concat(parameters('factoryName'), '/AbhishekDBSoruce_DS')]",
			"type": "Microsoft.DataFactory/factories/datasets",
			"apiVersion": "2018-06-01",
			"properties": {
				"linkedServiceName": {
					"referenceName": "AbhishekDB_LS",
					"type": "LinkedServiceReference"
				},
				"annotations": [],
				"type": "AzureSqlTable",
				"schema": [],
				"typeProperties": {
					"schema": "dbo",
					"table": "department"
				}
			},
			"dependsOn": [
				"[concat(variables('factoryId'), '/linkedServices/AbhishekDB_LS')]"
			]
		},
		{
			"name": "[concat(parameters('factoryName'), '/AbhishekSQLAll_DS')]",
			"type": "Microsoft.DataFactory/factories/datasets",
			"apiVersion": "2018-06-01",
			"properties": {
				"linkedServiceName": {
					"referenceName": "AbhishekDB_LS",
					"type": "LinkedServiceReference"
				},
				"parameters": {
					"AbhiSoruceSchema": {
						"type": "string"
					},
					"AbhiSoruceTable": {
						"type": "string"
					}
				},
				"annotations": [],
				"type": "AzureSqlTable",
				"schema": [],
				"typeProperties": {
					"schema": {
						"value": "@dataset().AbhiSoruceSchema",
						"type": "Expression"
					},
					"table": {
						"value": "@dataset().AbhiSoruceTable",
						"type": "Expression"
					}
				}
			},
			"dependsOn": [
				"[concat(variables('factoryId'), '/linkedServices/AbhishekDB_LS')]"
			]
		},
		{
			"name": "[concat(parameters('factoryName'), '/AbhishekSQLDatasource')]",
			"type": "Microsoft.DataFactory/factories/datasets",
			"apiVersion": "2018-06-01",
			"properties": {
				"linkedServiceName": {
					"referenceName": "AbhishekDB_LS",
					"type": "LinkedServiceReference"
				},
				"parameters": {
					"SourceSQLSchema": {
						"type": "string"
					},
					"SoruceSQLTable": {
						"type": "string"
					}
				},
				"annotations": [],
				"type": "AzureSqlTable",
				"schema": [],
				"typeProperties": {
					"schema": {
						"value": "@dataset().SourceSQLSchema",
						"type": "Expression"
					},
					"table": {
						"value": "@dataset().SoruceSQLTable",
						"type": "Expression"
					}
				}
			},
			"dependsOn": [
				"[concat(variables('factoryId'), '/linkedServices/AbhishekDB_LS')]"
			]
		},
		{
			"name": "[concat(parameters('factoryName'), '/ClientDB')]",
			"type": "Microsoft.DataFactory/factories/datasets",
			"apiVersion": "2018-06-01",
			"properties": {
				"linkedServiceName": {
					"referenceName": "ClientDBLinkedServer",
					"type": "LinkedServiceReference"
				},
				"annotations": [],
				"type": "AzureSqlTable",
				"schema": [],
				"typeProperties": {
					"schema": "dbo",
					"table": "StudentdataClient"
				}
			},
			"dependsOn": [
				"[concat(variables('factoryId'), '/linkedServices/ClientDBLinkedServer')]"
			]
		},
		{
			"name": "[concat(parameters('factoryName'), '/DeltaLoadStorageAccount')]",
			"type": "Microsoft.DataFactory/factories/datasets",
			"apiVersion": "2018-06-01",
			"properties": {
				"linkedServiceName": {
					"referenceName": "Gen2Storage_LS",
					"type": "LinkedServiceReference"
				},
				"annotations": [],
				"type": "DelimitedText",
				"typeProperties": {
					"location": {
						"type": "AzureBlobFSLocation",
						"fileName": "StudentDataDest.csv",
						"folderPath": {
							"value": "formatDateTime(utcnow(), 'dd-MMM-yyyy'))",
							"type": "Expression"
						},
						"fileSystem": "clientcontainer"
					},
					"columnDelimiter": ",",
					"escapeChar": "\\",
					"firstRowAsHeader": true,
					"quoteChar": "\""
				},
				"schema": []
			},
			"dependsOn": [
				"[concat(variables('factoryId'), '/linkedServices/Gen2Storage_LS')]"
			]
		},
		{
			"name": "[concat(parameters('factoryName'), '/DestBackup')]",
			"type": "Microsoft.DataFactory/factories/datasets",
			"apiVersion": "2018-06-01",
			"properties": {
				"linkedServiceName": {
					"referenceName": "Gen2Storage_LS",
					"type": "LinkedServiceReference"
				},
				"parameters": {
					"FileName": {
						"type": "string"
					}
				},
				"annotations": [],
				"type": "DelimitedText",
				"typeProperties": {
					"location": {
						"type": "AzureBlobFSLocation",
						"fileName": {
							"value": "@dataset().FileName",
							"type": "Expression"
						},
						"folderPath": "TablesCopy",
						"fileSystem": "container2"
					},
					"columnDelimiter": ",",
					"escapeChar": "\\",
					"firstRowAsHeader": true,
					"quoteChar": "\""
				},
				"schema": []
			},
			"dependsOn": [
				"[concat(variables('factoryId'), '/linkedServices/Gen2Storage_LS')]"
			]
		},
		{
			"name": "[concat(parameters('factoryName'), '/DestDS_Gen2')]",
			"type": "Microsoft.DataFactory/factories/datasets",
			"apiVersion": "2018-06-01",
			"properties": {
				"linkedServiceName": {
					"referenceName": "Gen2Storage_LS",
					"type": "LinkedServiceReference"
				},
				"parameters": {
					"OutFolderName": {
						"type": "string"
					},
					"OutFileName": {
						"type": "string"
					}
				},
				"annotations": [],
				"type": "DelimitedText",
				"typeProperties": {
					"location": {
						"type": "AzureBlobFSLocation",
						"fileName": {
							"value": "@dataset().OutFileName",
							"type": "Expression"
						},
						"folderPath": {
							"value": "@dataset().OutFolderName",
							"type": "Expression"
						},
						"fileSystem": "container2/ForeachOutput"
					},
					"columnDelimiter": ",",
					"escapeChar": "\\",
					"firstRowAsHeader": true,
					"quoteChar": "\""
				},
				"schema": []
			},
			"dependsOn": [
				"[concat(variables('factoryId'), '/linkedServices/Gen2Storage_LS')]"
			]
		},
		{
			"name": "[concat(parameters('factoryName'), '/DestGen2_DS')]",
			"type": "Microsoft.DataFactory/factories/datasets",
			"apiVersion": "2018-06-01",
			"properties": {
				"linkedServiceName": {
					"referenceName": "Gen2Storage_LS",
					"type": "LinkedServiceReference"
				},
				"parameters": {
					"FileName": {
						"type": "string"
					}
				},
				"annotations": [],
				"type": "DelimitedText",
				"typeProperties": {
					"location": {
						"type": "AzureBlobFSLocation",
						"fileName": {
							"value": "@dataset().FileName",
							"type": "Expression"
						},
						"folderPath": "TablesCopy",
						"fileSystem": "container2"
					},
					"columnDelimiter": ",",
					"escapeChar": "\\",
					"firstRowAsHeader": true,
					"quoteChar": "\""
				},
				"schema": []
			},
			"dependsOn": [
				"[concat(variables('factoryId'), '/linkedServices/Gen2Storage_LS')]"
			]
		},
		{
			"name": "[concat(parameters('factoryName'), '/DestMySQLDB_DS')]",
			"type": "Microsoft.DataFactory/factories/datasets",
			"apiVersion": "2018-06-01",
			"properties": {
				"linkedServiceName": {
					"referenceName": "sqlserversagarSagarDB_LS",
					"type": "LinkedServiceReference"
				},
				"parameters": {
					"DestSQLSchema": {
						"type": "string"
					},
					"DestSQLTable": {
						"type": "string"
					}
				},
				"annotations": [],
				"type": "AzureSqlTable",
				"schema": [],
				"typeProperties": {
					"schema": {
						"value": "@dataset().DestSQLSchema",
						"type": "Expression"
					},
					"table": {
						"value": "@dataset().DestSQLTable",
						"type": "Expression"
					}
				}
			},
			"dependsOn": [
				"[concat(variables('factoryId'), '/linkedServices/sqlserversagarSagarDB_LS')]"
			]
		},
		{
			"name": "[concat(parameters('factoryName'), '/DestSQLTable_DS')]",
			"type": "Microsoft.DataFactory/factories/datasets",
			"apiVersion": "2018-06-01",
			"properties": {
				"linkedServiceName": {
					"referenceName": "sqlserversagarSagarDB_LS",
					"type": "LinkedServiceReference"
				},
				"annotations": [],
				"type": "AzureSqlTable",
				"schema": [],
				"typeProperties": {
					"schema": "dbo",
					"table": "Metadata"
				}
			},
			"dependsOn": [
				"[concat(variables('factoryId'), '/linkedServices/sqlserversagarSagarDB_LS')]"
			]
		},
		{
			"name": "[concat(parameters('factoryName'), '/FinalDestSQL')]",
			"type": "Microsoft.DataFactory/factories/datasets",
			"apiVersion": "2018-06-01",
			"properties": {
				"linkedServiceName": {
					"referenceName": "sqlserversagarSagarDB_LS",
					"type": "LinkedServiceReference"
				},
				"parameters": {
					"DestSchema": {
						"type": "string"
					},
					"DestTable": {
						"type": "string"
					}
				},
				"annotations": [],
				"type": "AzureSqlTable",
				"schema": [],
				"typeProperties": {
					"schema": {
						"value": "@dataset().DestSchema",
						"type": "Expression"
					},
					"table": {
						"value": "@dataset().DestTable",
						"type": "Expression"
					}
				}
			},
			"dependsOn": [
				"[concat(variables('factoryId'), '/linkedServices/sqlserversagarSagarDB_LS')]"
			]
		},
		{
			"name": "[concat(parameters('factoryName'), '/Gen2SorucetoSQLTables')]",
			"type": "Microsoft.DataFactory/factories/datasets",
			"apiVersion": "2018-06-01",
			"properties": {
				"linkedServiceName": {
					"referenceName": "Gen2Storage_LS",
					"type": "LinkedServiceReference"
				},
				"parameters": {
					"InputFileName": {
						"type": "string"
					},
					"InputFolderName": {
						"type": "string"
					}
				},
				"annotations": [],
				"type": "DelimitedText",
				"typeProperties": {
					"location": {
						"type": "AzureBlobFSLocation",
						"fileName": {
							"value": "@dataset().InputFileName",
							"type": "Expression"
						},
						"folderPath": {
							"value": "@dataset().InputFolderName",
							"type": "Expression"
						},
						"fileSystem": "container2/ForeachOutput"
					},
					"columnDelimiter": ",",
					"escapeChar": "\\",
					"firstRowAsHeader": true,
					"quoteChar": "\""
				},
				"schema": []
			},
			"dependsOn": [
				"[concat(variables('factoryId'), '/linkedServices/Gen2Storage_LS')]"
			]
		}
	]
}